<annotation>
  <folder>myVOC</folder>
  <filename>Container-Door-(693).jpg</filename>
  <source>
    <database>Unknown</database>
  </source>
  <size>
    <width>625</width>
    <height>815</height>
    <depth>3</depth>
  </size>
  <segmented>0</segmented>
  <object>
    <name>container_door</name>
    <pose>Unspecified</pose>
    <truncated>0</truncated>
    <difficult>0</difficult>
    <bndbox>
      <xmin>15</xmin>
      <ymin>8</ymin>
      <xmax>611</xmax>
      <ymax>789</ymax>
    </bndbox>
  </object>
</annotation>