<annotation>
  <folder>myVOC</folder>
  <filename>Container-No-Door-(113).jpg</filename>
  <source>
    <database>Unknown</database>
  </source>
  <size>
    <width>2448</width>
    <height>3264</height>
    <depth>3</depth>
  </size>
  <segmented>0</segmented>
  <object>
    <name>container_no_door</name>
    <pose>Unspecified</pose>
    <truncated>0</truncated>
    <difficult>0</difficult>
    <bndbox>
      <xmin>757</xmin>
      <ymin>59</ymin>
      <xmax>1257</xmax>
      <ymax>534</ymax>
    </bndbox>
  </object>
  <object>
    <name>container_no_door</name>
    <pose>Unspecified</pose>
    <truncated>0</truncated>
    <difficult>0</difficult>
    <bndbox>
      <xmin>1307</xmin>
      <ymin>1184</ymin>
      <xmax>1569</xmax>
      <ymax>1467</ymax>
    </bndbox>
  </object>
  <object>
    <name>container_no_door</name>
    <pose>Unspecified</pose>
    <truncated>0</truncated>
    <difficult>0</difficult>
    <bndbox>
      <xmin>1305</xmin>
      <ymin>1465</ymin>
      <xmax>1567</xmax>
      <ymax>1748</ymax>
    </bndbox>
  </object>
  <object>
    <name>container_no_door</name>
    <pose>Unspecified</pose>
    <truncated>0</truncated>
    <difficult>0</difficult>
    <bndbox>
      <xmin>1403</xmin>
      <ymin>1580</ymin>
      <xmax>2053</xmax>
      <ymax>2284</ymax>
    </bndbox>
  </object>
  <object>
    <name>container_no_door</name>
    <pose>Unspecified</pose>
    <truncated>0</truncated>
    <difficult>0</difficult>
    <bndbox>
      <xmin>1443</xmin>
      <ymin>2282</ymin>
      <xmax>2182</xmax>
      <ymax>3104</ymax>
    </bndbox>
  </object>
  <object>
    <name>container_door</name>
    <pose>Unspecified</pose>
    <truncated>0</truncated>
    <difficult>0</difficult>
    <bndbox>
      <xmin>778</xmin>
      <ymin>529</ymin>
      <xmax>1278</xmax>
      <ymax>1042</ymax>
    </bndbox>
  </object>
  <object>
    <name>container_no_door</name>
    <pose>Unspecified</pose>
    <truncated>0</truncated>
    <difficult>0</difficult>
    <bndbox>
      <xmin>2099</xmin>
      <ymin>1709</ymin>
      <xmax>2448</xmax>
      <ymax>2342</ymax>
    </bndbox>
  </object>
  <object>
    <name>container_no_door</name>
    <pose>Unspecified</pose>
    <truncated>0</truncated>
    <difficult>0</difficult>
    <bndbox>
      <xmin>2144</xmin>
      <ymin>2340</ymin>
      <xmax>2448</xmax>
      <ymax>3046</ymax>
    </bndbox>
  </object>
</annotation>