<annotation>
  <folder>myVOC</folder>
  <filename>Container-No-Door-(579).jpg</filename>
  <source>
    <database>Unknown</database>
  </source>
  <size>
    <width>484</width>
    <height>588</height>
    <depth>3</depth>
  </size>
  <segmented>0</segmented>
  <object>
    <name>container_no_door</name>
    <pose>Unspecified</pose>
    <truncated>0</truncated>
    <difficult>0</difficult>
    <bndbox>
      <xmin>2</xmin>
      <ymin>14</ymin>
      <xmax>476</xmax>
      <ymax>582</ymax>
    </bndbox>
  </object>
</annotation>