<annotation>
  <folder>myVOC</folder>
  <filename>Container-No-Door-(533).jpg</filename>
  <source>
    <database>Unknown</database>
  </source>
  <size>
    <width>1297</width>
    <height>1379</height>
    <depth>3</depth>
  </size>
  <segmented>0</segmented>
  <object>
    <name>container_no_door</name>
    <pose>Unspecified</pose>
    <truncated>0</truncated>
    <difficult>0</difficult>
    <bndbox>
      <xmin>1</xmin>
      <ymin>9</ymin>
      <xmax>1269</xmax>
      <ymax>1356</ymax>
    </bndbox>
  </object>
</annotation>