<annotation>
  <folder>data</folder>
  <filename>Wagon-Scan-(13)</filename>
  <path>D:\_MA\psychic-memory\Label Tools\LabelImg\data\Wagon-Scan-(13).jpg</path>
  <source>
    <database>Unknown</database>
  </source>
  <size>
    <width>352</width>
    <height>288</height>
    <depth>1</depth>
  </size>
  <segmented>0</segmented>
  <object>
    <name>wagon_scan</name>
    <pose>Unspecified</pose>
    <truncated>0</truncated>
    <difficult>0</difficult>
    <bndbox>
      <xmin>145</xmin>
      <ymin>100</ymin>
      <xmax>212</xmax>
      <ymax>141</ymax>
    </bndbox>
  </object>
</annotation>
